gwopensci/__init__.py
gwopensci/_version.py
gwopensci/api.py
gwopensci/datasets.py
gwopensci/locate.py
gwopensci/test_gwopensci.py
gwopensci/timeline.py
gwopensci/urls.py
gwopensci/utils.py
gwopensci-0.2.1.dist-info/DESCRIPTION.rst
gwopensci-0.2.1.dist-info/METADATA
gwopensci-0.2.1.dist-info/RECORD
gwopensci-0.2.1.dist-info/WHEEL
gwopensci-0.2.1.dist-info/metadata.json
gwopensci-0.2.1.dist-info/top_level.txt
